{
    "sources": [
        {
            "include": false,
            "name": "16145213@N00",
            "service": "flickr",
            "age": 29,
            "engagement": 0,
            "volume": -1,
            "frequency": 29,
            "score": 14447,
            "type": "common"
        },
        {
            "include": true,
            "name": "1895848@N22",
            "service": "flickr",
            "age": -28,
            "engagement": -1,
            "volume": -1,
            "frequency": -23,
            "score": 48054,
            "type": "common"
        },
        {
            "include": false,
            "name": "652875@N24",
            "service": "flickr",
            "age": -6,
            "engagement": -1,
            "volume": 0,
            "frequency": 6,
            "score": 6963,
            "type": "common"
        },
        {
            "include": false,
            "name": "31379270@N00",
            "service": "flickr",
            "age": 0,
            "engagement": 0,
            "volume": 0,
            "frequency": -12,
            "score": 2747,
            "type": "common"
        },
        {
            "include": false,
            "name": "1311161@N23",
            "service": "flickr",
            "age": 4,
            "engagement": 0,
            "volume": 0,
            "frequency": 11,
            "score": 23146,
            "type": "common"
        },
        {
            "include": false,
            "name": "14043066@N00",
            "service": "flickr",
            "age": 19,
            "engagement": -1,
            "volume": 0,
            "frequency": 34,
            "score": 21826,
            "type": "common"
        },
        {
            "include": false,
            "name": "1637508@N25",
            "service": "flickr",
            "age": 8,
            "engagement": 1,
            "volume": 0,
            "frequency": 3,
            "score": 29668,
            "type": "common"
        },
        {
            "include": true,
            "name": "1895848@N22",
            "service": "flickr",
            "age": -28,
            "engagement": -1,
            "volume": -1,
            "frequency": -23,
            "score": 48054,
            "type": "common"
        },
        {
            "include": false,
            "name": "73158265@N00",
            "service": "flickr",
            "age": 33,
            "engagement": 1,
            "volume": -1,
            "frequency": 43,
            "score": 671,
            "type": "common"
        },
        {
            "include": false,
            "name": "1500066@N23",
            "service": "flickr",
            "age": 24,
            "engagement": 0,
            "volume": 0,
            "frequency": 19,
            "score": 3081,
            "type": "common"
        },
        {
            "include": false,
            "name": "1311161@N23",
            "service": "flickr",
            "age": 4,
            "engagement": 0,
            "volume": 0,
            "frequency": 11,
            "score": 23146,
            "type": "common"
        },
        {
            "include": false,
            "name": "629689@N23",
            "service": "flickr",
            "age": -18,
            "engagement": 0,
            "volume": 1,
            "frequency": -16,
            "score": 9458,
            "type": "common"
        },
        {
            "include": false,
            "name": "93785638@N00",
            "service": "flickr",
            "age": -42,
            "engagement": 0,
            "volume": 1,
            "frequency": -41,
            "score": 1630,
            "type": "common"
        },
        {
            "include": false,
            "name": "1377046@N25",
            "service": "flickr",
            "age": -10,
            "engagement": 1,
            "volume": 0,
            "frequency": -3,
            "score": 11167,
            "type": "common"
        },
        {
            "include": false,
            "name": "39332863@N00",
            "service": "flickr",
            "age": -37,
            "engagement": 0,
            "volume": 0,
            "frequency": -34,
            "score": 7725,
            "type": "common"
        },
        {
            "include": false,
            "name": "1456683@N24",
            "service": "flickr",
            "age": 9,
            "engagement": 0,
            "volume": 0,
            "frequency": -40,
            "score": 5843,
            "type": "common"
        },
        {
            "include": false,
            "name": "1490263@N22",
            "service": "flickr",
            "age": -34,
            "engagement": -1,
            "volume": 1,
            "frequency": -31,
            "score": 29981,
            "type": "common"
        },
        {
            "include": false,
            "name": "584254@N21",
            "service": "flickr",
            "age": -27,
            "engagement": 1,
            "volume": 0,
            "frequency": -34,
            "score": 5936,
            "type": "common"
        },
        {
            "include": false,
            "name": "1702851@N22",
            "service": "flickr",
            "age": -24,
            "engagement": 0,
            "volume": 0,
            "frequency": -31,
            "score": 7823,
            "type": "common"
        },
        {
            "include": false,
            "name": "1637508@N25",
            "service": "flickr",
            "age": 8,
            "engagement": 1,
            "volume": 0,
            "frequency": 3,
            "score": 29668,
            "type": "common"
        },
        {
            "include": false,
            "name": "81313319@N00",
            "service": "flickr",
            "age": -39,
            "engagement": 1,
            "volume": -1,
            "frequency": -37,
            "score": 11434,
            "type": "common"
        },
        {
            "include": false,
            "name": "73158265@N00",
            "service": "flickr",
            "age": 33,
            "engagement": 1,
            "volume": -1,
            "frequency": 43,
            "score": 671,
            "type": "common"
        },
        {
            "include": false,
            "name": "16719610@N00",
            "service": "flickr",
            "age": 37,
            "engagement": 1,
            "volume": 0,
            "frequency": 32,
            "score": 6817,
            "type": "common"
        },
        {
            "include": false,
            "name": "35628714@N00",
            "service": "flickr",
            "age": 17,
            "engagement": 1,
            "volume": 0,
            "frequency": 22,
            "score": 6575,
            "type": "common"
        },
        {
            "include": false,
            "name": "67145394@N00",
            "service": "flickr",
            "age": 12,
            "engagement": 1,
            "volume": 0,
            "frequency": 30,
            "score": 350,
            "type": "common"
        },
        {
            "include": false,
            "name": "619245@N25",
            "service": "flickr",
            "age": -13,
            "engagement": 0,
            "volume": 0,
            "frequency": -11,
            "score": 5390,
            "type": "common"
        },
        {
            "include": false,
            "name": "14043066@N00",
            "service": "flickr",
            "age": 19,
            "engagement": -1,
            "volume": 0,
            "frequency": 34,
            "score": 21826,
            "type": "common"
        },
        {
            "include": true,
            "name": "1895848@N22",
            "service": "flickr",
            "age": -28,
            "engagement": -1,
            "volume": -1,
            "frequency": -23,
            "score": 48054,
            "type": "common"
        },
        {
            "include": false,
            "name": "16145213@N00",
            "service": "flickr",
            "age": 29,
            "engagement": 0,
            "volume": -1,
            "frequency": 29,
            "score": 14447,
            "type": "common"
        },
        {
            "include": false,
            "name": "1627317@N22",
            "service": "flickr",
            "age": -38,
            "engagement": 0,
            "volume": 0,
            "frequency": -49,
            "score": 37100,
            "type": "common"
        },
        {
            "include": false,
            "name": "93785638@N00",
            "service": "flickr",
            "age": -42,
            "engagement": 0,
            "volume": 1,
            "frequency": -41,
            "score": 1630,
            "type": "common"
        },
        {
            "include": false,
            "name": "86521483@N00",
            "service": "flickr",
            "age": -49,
            "engagement": 1,
            "volume": 1,
            "frequency": -48,
            "score": 7158,
            "type": "common"
        },
        {
            "include": false,
            "name": "1095245@N20",
            "service": "flickr",
            "age": -35,
            "engagement": 0,
            "volume": 0,
            "frequency": -30,
            "score": 7882,
            "type": "common"
        },
        {
            "include": false,
            "name": "52242317293@N01",
            "service": "flickr",
            "age": -50,
            "engagement": -1,
            "volume": 1,
            "frequency": -49,
            "score": 8933,
            "type": "common"
        },
        {
            "include": false,
            "name": "390652@N22",
            "service": "flickr",
            "age": -21,
            "engagement": 0,
            "volume": -1,
            "frequency": -19,
            "score": 41746,
            "type": "common"
        },
        {
            "include": false,
            "name": "1895848@N22",
            "service": "flickr",
            "age": -28,
            "engagement": -1,
            "volume": -1,
            "frequency": -23,
            "score": 48054,
            "type": "common"
        },
        {
            "include": false,
            "name": "652875@N24",
            "service": "flickr",
            "age": -6,
            "engagement": -1,
            "volume": 0,
            "frequency": 6,
            "score": 6963,
            "type": "common"
        },
        {
            "include": false,
            "name": "16145213@N00",
            "service": "flickr",
            "age": 29,
            "engagement": 0,
            "volume": -1,
            "frequency": 29,
            "score": 14447,
            "type": "common"
        },
        {
            "include": false,
            "name": "65763105@N00",
            "service": "flickr",
            "age": -20,
            "engagement": 0,
            "volume": 0,
            "frequency": -28,
            "score": 13200,
            "type": "common"
        },
        {
            "include": false,
            "name": "1895848@N22",
            "service": "flickr",
            "age": -28,
            "engagement": -1,
            "volume": -1,
            "frequency": -23,
            "score": 48054,
            "type": "common"
        },
        {
            "include": false,
            "name": "73158265@N00",
            "service": "flickr",
            "age": 33,
            "engagement": 1,
            "volume": -1,
            "frequency": 43,
            "score": 671,
            "type": "common"
        },
        {
            "include": false,
            "name": "541069@N24",
            "service": "flickr",
            "age": 41,
            "engagement": 1,
            "volume": -1,
            "frequency": 24,
            "score": 3343,
            "type": "common"
        },
        {
            "include": false,
            "name": "390652@N22",
            "service": "flickr",
            "age": -21,
            "engagement": 0,
            "volume": -1,
            "frequency": -19,
            "score": 41746,
            "type": "common"
        },
        {
            "include": false,
            "name": "1637508@N25",
            "service": "flickr",
            "age": 8,
            "engagement": 1,
            "volume": 0,
            "frequency": 3,
            "score": 29668,
            "type": "common"
        },
        {
            "include": false,
            "name": "1500066@N23",
            "service": "flickr",
            "age": 24,
            "engagement": 0,
            "volume": 0,
            "frequency": 19,
            "score": 3081,
            "type": "common"
        },
        {
            "include": false,
            "name": "1702851@N22",
            "service": "flickr",
            "age": -24,
            "engagement": 0,
            "volume": 0,
            "frequency": -31,
            "score": 7823,
            "type": "common"
        },
        {
            "include": false,
            "name": "652875@N24",
            "service": "flickr",
            "age": -6,
            "engagement": -1,
            "volume": 0,
            "frequency": 6,
            "score": 6963,
            "type": "common"
        },
        {
            "include": false,
            "name": "93785638@N00",
            "service": "flickr",
            "age": -42,
            "engagement": 0,
            "volume": 1,
            "frequency": -41,
            "score": 1630,
            "type": "common"
        },
        {
            "include": false,
            "name": "1311161@N23",
            "service": "flickr",
            "age": 4,
            "engagement": 0,
            "volume": 0,
            "frequency": 11,
            "score": 23146,
            "type": "common"
        },
        {
            "include": false,
            "name": "16145213@N00",
            "service": "flickr",
            "age": 29,
            "engagement": 0,
            "volume": -1,
            "frequency": 29,
            "score": 14447,
            "type": "common"
        },
        {
            "include": false,
            "name": "629689@N23",
            "service": "flickr",
            "age": -18,
            "engagement": 0,
            "volume": 1,
            "frequency": -16,
            "score": 9458,
            "type": "common"
        },
        {
            "include": false,
            "name": "1377046@N25",
            "service": "flickr",
            "age": -10,
            "engagement": 1,
            "volume": 0,
            "frequency": -3,
            "score": 11167,
            "type": "common"
        },
        {
            "include": false,
            "name": "306139@N24",
            "service": "flickr",
            "age": 30,
            "engagement": 1,
            "volume": 0,
            "frequency": 39,
            "score": 3111,
            "type": "common"
        },
        {
            "include": false,
            "name": "60514301@N00",
            "service": "flickr",
            "age": 13,
            "engagement": 1,
            "volume": 0,
            "frequency": 16,
            "score": 3843,
            "type": "common"
        },
        {
            "include": false,
            "name": "1188695@N25",
            "service": "flickr",
            "age": -4,
            "engagement": 0,
            "volume": 1,
            "frequency": 0,
            "score": 7290,
            "type": "common"
        },
        {
            "include": false,
            "name": "1065300@N21",
            "service": "flickr",
            "age": -14,
            "engagement": 1,
            "volume": 1,
            "frequency": -13,
            "score": 11830,
            "type": "common"
        },
        {
            "include": false,
            "name": "1041854@N22",
            "service": "flickr",
            "age": 34,
            "engagement": -1,
            "volume": -1,
            "frequency": 31,
            "score": 7269,
            "type": "common"
        },
        {
            "include": false,
            "name": "46504746@N00",
            "service": "flickr",
            "age": -26,
            "engagement": 0,
            "volume": 1,
            "frequency": -19,
            "score": 9052,
            "type": "common"
        },
        {
            "include": false,
            "name": "551563@N21",
            "service": "flickr",
            "age": -2,
            "engagement": 0,
            "volume": 1,
            "frequency": -6,
            "score": 5612,
            "type": "common"
        },
        {
            "include": false,
            "name": "1451707@N25",
            "service": "flickr",
            "age": 11,
            "engagement": -1,
            "volume": 1,
            "frequency": -9,
            "score": 6130,
            "type": "common"
        },
        {
            "include": false,
            "name": "1500066@N23",
            "service": "flickr",
            "age": 24,
            "engagement": 0,
            "volume": 0,
            "frequency": 19,
            "score": 3081,
            "type": "common"
        },
        {
            "include": false,
            "name": "756513@N22",
            "service": "flickr",
            "age": 38,
            "engagement": 1,
            "volume": -1,
            "frequency": 38,
            "score": 6852,
            "type": "common"
        },
        {
            "include": false,
            "name": "1373913@N20",
            "service": "flickr",
            "age": 40,
            "engagement": 1,
            "volume": 1,
            "frequency": 13,
            "score": 7601,
            "type": "common"
        },
        {
            "include": false,
            "name": "92921642@N00",
            "service": "flickr",
            "age": 36,
            "engagement": -1,
            "volume": -1,
            "frequency": 49,
            "score": 5448,
            "type": "common"
        },
        {
            "include": false,
            "name": "96935396@N00",
            "service": "flickr",
            "age": 49,
            "engagement": 0,
            "volume": -1,
            "frequency": 37,
            "score": 9432,
            "type": "common"
        },
        {
            "include": false,
            "name": "1781890@N23",
            "service": "flickr",
            "age": -48,
            "engagement": 0,
            "volume": 1,
            "frequency": -47,
            "score": 8324,
            "type": "common"
        },
        {
            "include": false,
            "name": "79835005@N00",
            "service": "flickr",
            "age": 16,
            "engagement": -1,
            "volume": -1,
            "frequency": 23,
            "score": 6810,
            "type": "common"
        },
        {
            "include": false,
            "name": "1311161@N23",
            "service": "flickr",
            "age": 4,
            "engagement": 0,
            "volume": 0,
            "frequency": 11,
            "score": 23146,
            "type": "common"
        },
        {
            "include": false,
            "name": "629689@N23",
            "service": "flickr",
            "age": -18,
            "engagement": 0,
            "volume": 1,
            "frequency": -16,
            "score": 9458,
            "type": "common"
        },
        {
            "include": false,
            "name": "1377046@N25",
            "service": "flickr",
            "age": -10,
            "engagement": 1,
            "volume": 0,
            "frequency": -3,
            "score": 11167,
            "type": "common"
        },
        {
            "include": false,
            "name": "1188695@N25",
            "service": "flickr",
            "age": -4,
            "engagement": 0,
            "volume": 1,
            "frequency": 0,
            "score": 7290,
            "type": "common"
        },
        {
            "include": false,
            "name": "1451707@N25",
            "service": "flickr",
            "age": 11,
            "engagement": -1,
            "volume": 1,
            "frequency": -9,
            "score": 6130,
            "type": "common"
        },
        {
            "include": false,
            "name": "96935396@N00",
            "service": "flickr",
            "age": 49,
            "engagement": 0,
            "volume": -1,
            "frequency": 37,
            "score": 9432,
            "type": "common"
        },
        {
            "include": false,
            "name": "1500066@N23",
            "service": "flickr",
            "age": 24,
            "engagement": 0,
            "volume": 0,
            "frequency": 19,
            "score": 3081,
            "type": "common"
        },
        {
            "include": false,
            "name": "1373913@N20",
            "service": "flickr",
            "age": 40,
            "engagement": 1,
            "volume": 1,
            "frequency": 13,
            "score": 7601,
            "type": "common"
        },
        {
            "include": false,
            "name": "551563@N21",
            "service": "flickr",
            "age": -2,
            "engagement": 0,
            "volume": 1,
            "frequency": -6,
            "score": 5612,
            "type": "common"
        },
        {
            "include": false,
            "name": "1206579@N25",
            "service": "flickr",
            "age": 15,
            "engagement": 0,
            "volume": 0,
            "frequency": 15,
            "score": 3422,
            "type": "common"
        },
        {
            "include": false,
            "name": "1593811@N20",
            "service": "flickr",
            "age": -41,
            "engagement": 0,
            "volume": 1,
            "frequency": -39,
            "score": 2859,
            "type": "common"
        },
        {
            "include": false,
            "name": "1108488@N21",
            "service": "flickr",
            "age": -40,
            "engagement": -1,
            "volume": 1,
            "frequency": -37,
            "score": 9233,
            "type": "common"
        },
        {
            "include": false,
            "name": "1065300@N21",
            "service": "flickr",
            "age": -14,
            "engagement": 1,
            "volume": 1,
            "frequency": -13,
            "score": 11830,
            "type": "common"
        },
        {
            "include": false,
            "name": "http://eyadah.tumblr.com/",
            "service": "tumblr",
            "age": -37,
            "engagement": 0,
            "volume": 0,
            "frequency": -29,
            "score": 1768,
            "type": "common"
        },
        {
            "include": false,
            "name": "http://refugeeartproject.tumblr.com/",
            "service": "tumblr",
            "age": -29,
            "engagement": 1,
            "volume": 0,
            "frequency": -24,
            "score": 4186,
            "type": "common"
        },
        {
            "include": false,
            "name": "http://resistance-episteme.tumblr.com/",
            "service": "tumblr",
            "age": 36,
            "engagement": 0,
            "volume": 0,
            "frequency": 41,
            "score": 4358,
            "type": "common"
        },
        {
            "include": false,
            "name": "http://orkideh84.tumblr.com/",
            "service": "tumblr",
            "age": -42,
            "engagement": 1,
            "volume": 1,
            "frequency": -37,
            "score": 303,
            "type": "common"
        },
        {
            "include": false,
            "name": "http://leftieskerthings.tumblr.com/",
            "service": "tumblr",
            "age": -50,
            "engagement": -1,
            "volume": 1,
            "frequency": -37,
            "score": 1277,
            "type": "common"
        },
        {
            "include": false,
            "name": "http://hilalchouman.tumblr.com/",
            "service": "tumblr",
            "age": -20,
            "engagement": 0,
            "volume": 1,
            "frequency": -7,
            "score": 1999,
            "type": "common"
        },
        {
            "include": false,
            "name": "http://arwad88.tumblr.com/",
            "service": "tumblr",
            "age": 6,
            "engagement": 1,
            "volume": -1,
            "frequency": 10,
            "score": 918,
            "type": "common"
        },
        {
            "include": false,
            "name": "http://aonsyr.tumblr.com/",
            "service": "tumblr",
            "age": 23,
            "engagement": 0,
            "volume": 0,
            "frequency": 23,
            "score": 3253,
            "type": "common"
        },
        {
            "include": false,
            "name": "http://ad3yya.tumblr.com/",
            "service": "tumblr",
            "age": -46,
            "engagement": -1,
            "volume": 0,
            "frequency": -29,
            "score": 3708,
            "type": "common"
        },
        {
            "include": false,
            "name": "http://o-h2.tumblr.com/",
            "service": "tumblr",
            "age": -16,
            "engagement": 0,
            "volume": 0,
            "frequency": -7,
            "score": 4947,
            "type": "common"
        },
        {
            "include": true,
            "name": "http://drmeem.tumblr.com/",
            "service": "tumblr",
            "age": -11,
            "engagement": 0,
            "volume": 0,
            "frequency": 2,
            "score": 14999,
            "type": "common"
        },
        {
            "include": false,
            "name": "http://isloom.tumblr.com/",
            "service": "tumblr",
            "age": 10,
            "engagement": -1,
            "volume": 0,
            "frequency": 15,
            "score": 5215,
            "type": "common"
        },
        {
            "include": false,
            "name": "http://sh91.tumblr.com/",
            "service": "tumblr",
            "age": -24,
            "engagement": 1,
            "volume": -1,
            "frequency": -16,
            "score": 301,
            "type": "common"
        },
        {
            "include": false,
            "name": "http://justanotherpalestinian.tumblr.com/",
            "service": "tumblr",
            "age": -33,
            "engagement": -1,
            "volume": 1,
            "frequency": -37,
            "score": 371,
            "type": "common"
        },
        {
            "include": true,
            "name": "http://vanoos.tumblr.com/",
            "service": "tumblr",
            "age": 45,
            "engagement": 0,
            "volume": 1,
            "frequency": -50,
            "score": 7960,
            "type": "common"
        },
        {
            "include": false,
            "name": "http://thevoiceofsyria.tumblr.com/",
            "service": "tumblr",
            "age": 32,
            "engagement": 0,
            "volume": -1,
            "frequency": 36,
            "score": 7643,
            "type": "common"
        },
        {
            "include": false,
            "name": "http://moniseum.com/",
            "service": "tumblr",
            "age": -3,
            "engagement": -1,
            "volume": 0,
            "frequency": 2,
            "score": 4578,
            "type": "common"
        },
        {
            "include": false,
            "name": "http://byhiba.tumblr.com/",
            "service": "tumblr",
            "age": 41,
            "engagement": 1,
            "volume": -1,
            "frequency": 45,
            "score": 3128,
            "type": "common"
        },
        {
            "include": false,
            "name": "http://zakiyh.tumblr.com/",
            "service": "tumblr",
            "age": 15,
            "engagement": 0,
            "volume": -1,
            "frequency": 19,
            "score": 1947,
            "type": "common"
        },
        {
            "include": false,
            "name": "http://elizrael.tumblr.com/",
            "service": "tumblr",
            "age": 49,
            "engagement": 0,
            "volume": 0,
            "frequency": 49,
            "score": 3208,
            "type": "common"
        },
        {
            "include": true,
            "name": "http://speakup4syrianchildren.tumblr.com/",
            "service": "tumblr",
            "age": 19,
            "engagement": 0,
            "volume": -1,
            "frequency": 28,
            "score": 9419,
            "type": "common"
        },
        {
            "include": false,
            "name": "http://duntherpomuk.tumblr.com/",
            "service": "tumblr",
            "age": -7,
            "engagement": 0,
            "volume": 0,
            "frequency": 6,
            "score": 2442,
            "type": "common"
        },
        {
            "include": false,
            "name": "http://bob-ers.tumblr.com/",
            "service": "tumblr",
            "age": 28,
            "engagement": -1,
            "volume": 1,
            "frequency": 32,
            "score": 204,
            "type": "common"
        },
        {
            "include": false,
            "name": "http://iiwwttbbmm.tumblr.com/",
            "service": "tumblr",
            "age": 2,
            "engagement": 1,
            "volume": 0,
            "frequency": -16,
            "score": 939,
            "type": "common"
        },
        {
            "include": false,
            "name": "joshua_landis",
            "service": "twitter",
            "age": -3,
            "engagement": 0,
            "volume": -1,
            "frequency": -7,
            "score": 461,
            "type": "common"
        },
        {
            "include": false,
            "name": "SyriaDeeply",
            "service": "twitter",
            "age": -17,
            "engagement": 0,
            "volume": -1,
            "frequency": -19,
            "score": 2305,
            "type": "common"
        },
        {
            "include": false,
            "name": "RevolutionSyria",
            "service": "twitter",
            "age": -46,
            "engagement": 0,
            "volume": 1,
            "frequency": -44,
            "score": 2157,
            "type": "common"
        },
        {
            "include": false,
            "name": "Free_Media_Hub",
            "service": "twitter",
            "age": -46,
            "engagement": -1,
            "volume": 1,
            "frequency": -44,
            "score": 655,
            "type": "common"
        },
        {
            "include": false,
            "name": "LizSly",
            "service": "twitter",
            "age": -13,
            "engagement": 1,
            "volume": -1,
            "frequency": -7,
            "score": 72,
            "type": "common"
        },
        {
            "include": false,
            "name": "wissamtarif",
            "service": "twitter",
            "age": 3,
            "engagement": 0,
            "volume": 0,
            "frequency": 15,
            "score": 1946,
            "type": "common"
        },
        {
            "include": false,
            "name": "SyriaCampaigns",
            "service": "twitter",
            "age": 17,
            "engagement": 0,
            "volume": 0,
            "frequency": 24,
            "score": 2072,
            "type": "common"
        },
        {
            "include": false,
            "name": "ObeidaNahas",
            "service": "twitter",
            "age": 23,
            "engagement": 0,
            "volume": -1,
            "frequency": 34,
            "score": 2957,
            "type": "common"
        },
        {
            "include": false,
            "name": "Samsomhoms",
            "service": "twitter",
            "age": 36,
            "engagement": 0,
            "volume": 0,
            "frequency": 20,
            "score": 5944,
            "type": "common"
        },
        {
            "include": false,
            "name": "jenanmoussa",
            "service": "twitter",
            "age": -26,
            "engagement": 1,
            "volume": 0,
            "frequency": 1,
            "score": 819,
            "type": "common"
        },
        {
            "include": false,
            "name": "samdagher",
            "service": "twitter",
            "age": -16,
            "engagement": 0,
            "volume": -1,
            "frequency": -19,
            "score": 5681,
            "type": "common"
        },
        {
            "include": false,
            "name": "AlexanderPageSY",
            "service": "twitter",
            "age": 0,
            "engagement": 0,
            "volume": 0,
            "frequency": 6,
            "score": 3098,
            "type": "common"
        },
        {
            "include": false,
            "name": "SANA_English",
            "service": "twitter",
            "age": -40,
            "engagement": -1,
            "volume": 0,
            "frequency": -19,
            "score": 3912,
            "type": "common"
        },
        {
            "include": false,
            "name": "SyrianJasmine",
            "service": "twitter",
            "age": 27,
            "engagement": -1,
            "volume": 0,
            "frequency": 31,
            "score": 4981,
            "type": "common"
        },
        {
            "include": false,
            "name": "Mar15Syria",
            "service": "twitter",
            "age": 34,
            "engagement": -1,
            "volume": 0,
            "frequency": 49,
            "score": 2329,
            "type": "common"
        },
        {
            "include": false,
            "name": "Charles_Lister",
            "service": "twitter",
            "age": -2,
            "engagement": 0,
            "volume": 0,
            "frequency": 1,
            "score": 2184,
            "type": "common"
        },
        {
            "include": false,
            "name": "RedRazan",
            "service": "twitter",
            "age": 9,
            "engagement": 1,
            "volume": -1,
            "frequency": 15,
            "score": 797,
            "type": "common"
        },
        {
            "include": false,
            "name": "Syria_AlHadath",
            "service": "twitter",
            "age": -11,
            "engagement": 1,
            "volume": 1,
            "frequency": -19,
            "score": 4839,
            "type": "common"
        },
        {
            "include": false,
            "name": "rallaf",
            "service": "twitter",
            "age": 15,
            "engagement": -1,
            "volume": 0,
            "frequency": 22,
            "score": 3021,
            "type": "common"
        },
        {
            "include": false,
            "name": "SyrCoalition",
            "service": "twitter",
            "age": -26,
            "engagement": 0,
            "volume": -1,
            "frequency": -19,
            "score": 982,
            "type": "common"
        },
        {
            "include": false,
            "name": "ForwardSy",
            "service": "twitter",
            "age": 24,
            "engagement": 0,
            "volume": -1,
            "frequency": 33,
            "score": 1834,
            "type": "common"
        },
        {
            "include": false,
            "name": "Syria_homs1",
            "service": "twitter",
            "age": -5,
            "engagement": 1,
            "volume": 0,
            "frequency": 4,
            "score": 587,
            "type": "common"
        },
        {
            "include": false,
            "name": "horanson",
            "service": "twitter",
            "age": 32,
            "engagement": 0,
            "volume": -1,
            "frequency": 19,
            "score": 7528,
            "type": "common"
        },
        {
            "include": false,
            "name": "Lara",
            "service": "twitter",
            "age": 13,
            "engagement": 1,
            "volume": 0,
            "frequency": 25,
            "score": 859,
            "type": "common"
        },
        {
            "include": false,
            "name": "Yathalema",
            "service": "twitter",
            "age": -30,
            "engagement": 0,
            "volume": 1,
            "frequency": -19,
            "score": 5566,
            "type": "common"
        },
        {
            "include": false,
            "name": "Syria_AlHadath",
            "service": "twitter",
            "age": -11,
            "engagement": 1,
            "volume": 1,
            "frequency": -19,
            "score": 4839,
            "type": "common"
        },
        {
            "include": false,
            "name": "alRifai1",
            "service": "twitter",
            "age": -28,
            "engagement": 0,
            "volume": 1,
            "frequency": -19,
            "score": 2621,
            "type": "common"
        },
        {
            "include": false,
            "name": "HadiAlabdallah",
            "service": "twitter",
            "age": 11,
            "engagement": 1,
            "volume": -1,
            "frequency": 15,
            "score": 943,
            "type": "common"
        },
        {
            "include": false,
            "name": "AlArabiya_SY",
            "service": "twitter",
            "age": -23,
            "engagement": 1,
            "volume": 0,
            "frequency": -7,
            "score": 5869,
            "type": "common"
        },
        {
            "include": false,
            "name": "Sham_Brigades",
            "service": "twitter",
            "age": 26,
            "engagement": 1,
            "volume": 1,
            "frequency": 6,
            "score": 2082,
            "type": "common"
        },
        {
            "include": false,
            "name": "syria_alaan",
            "service": "twitter",
            "age": 6,
            "engagement": 0,
            "volume": 1,
            "frequency": 8,
            "score": 5520,
            "type": "common"
        },
        {
            "include": false,
            "name": "us_4_all",
            "service": "twitter",
            "age": 1,
            "engagement": 1,
            "volume": 0,
            "frequency": 4,
            "score": 2477,
            "type": "common"
        },
        {
            "include": false,
            "name": "SyriaGlory",
            "service": "twitter",
            "age": 19,
            "engagement": -1,
            "volume": 1,
            "frequency": -7,
            "score": 5931,
            "type": "common"
        },
        {
            "include": false,
            "name": "riyadhalasaad",
            "service": "twitter",
            "age": -10,
            "engagement": 1,
            "volume": 0,
            "frequency": -19,
            "score": 216,
            "type": "common"
        },
        {
            "include": false,
            "name": "bathn_allah",
            "service": "twitter",
            "age": -4,
            "engagement": 1,
            "volume": 1,
            "frequency": 1,
            "score": 642,
            "type": "common"
        },
        {
            "include": false,
            "name": "Word_Sawa",
            "service": "twitter",
            "age": -33,
            "engagement": 0,
            "volume": 1,
            "frequency": -19,
            "score": 1197,
            "type": "common"
        },
        {
            "include": false,
            "name": "shaamnews",
            "service": "twitter",
            "age": -45,
            "engagement": 0,
            "volume": 1,
            "frequency": -19,
            "score": 7327,
            "type": "common"
        },
        {
            "include": true,
            "name": "4__SYRIA",
            "service": "twitter",
            "age": 20,
            "engagement": 0,
            "volume": 1,
            "frequency": 32,
            "score": 12377,
            "type": "common"
        },
        {
            "include": false,
            "name": "4SYIQ",
            "service": "twitter",
            "age": -42,
            "engagement": 1,
            "volume": 0,
            "frequency": -19,
            "score": 646,
            "type": "common"
        },
        {
            "include": false,
            "name": "aimanaibrahem",
            "service": "twitter",
            "age": -21,
            "engagement": 0,
            "volume": 0,
            "frequency": -7,
            "score": 659,
            "type": "common"
        },
        {
            "include": false,
            "name": "freearmy29",
            "service": "twitter",
            "age": -33,
            "engagement": 0,
            "volume": 1,
            "frequency": -19,
            "score": 411,
            "type": "common"
        },
        {
            "include": false,
            "name": "jabhasyria",
            "service": "twitter",
            "age": 33,
            "engagement": 0,
            "volume": -1,
            "frequency": 29,
            "score": 2,
            "type": "common"
        },
        {
            "include": false,
            "name": "NewsSyRev",
            "service": "twitter",
            "age": -30,
            "engagement": 0,
            "volume": 1,
            "frequency": -19,
            "score": 5319,
            "type": "common"
        },
        {
            "include": false,
            "name": "AbuYazanAlshami",
            "service": "twitter",
            "age": 12,
            "engagement": 1,
            "volume": -1,
            "frequency": 18,
            "score": 1933,
            "type": "common"
        },
        {
            "include": false,
            "name": "abuomerq8",
            "service": "twitter",
            "age": -38,
            "engagement": 0,
            "volume": 1,
            "frequency": -19,
            "score": 37,
            "type": "common"
        },
        {
            "include": false,
            "name": "souriaalasd",
            "service": "twitter",
            "age": -13,
            "engagement": -1,
            "volume": 0,
            "frequency": -19,
            "score": 356,
            "type": "common"
        },
        {
            "include": false,
            "name": "Syria_Breaking",
            "service": "twitter",
            "age": 4,
            "engagement": 0,
            "volume": 0,
            "frequency": 9,
            "score": 153,
            "type": "common"
        },
        {
            "include": false,
            "name": "AdnanAlarour",
            "service": "twitter",
            "age": 3,
            "engagement": 1,
            "volume": -1,
            "frequency": 15,
            "score": 150,
            "type": "common"
        },
        {
            "include": false,
            "name": "Syria_homs1",
            "service": "twitter",
            "age": -5,
            "engagement": 1,
            "volume": 0,
            "frequency": 4,
            "score": 587,
            "type": "common"
        },
        {
            "include": false,
            "name": "anwarmalek",
            "service": "twitter",
            "age": -37,
            "engagement": 1,
            "volume": 0,
            "frequency": -19,
            "score": 2350,
            "type": "common"
        },
        {
            "include": false,
            "name": "shammarF16",
            "service": "twitter",
            "age": 5,
            "engagement": 1,
            "volume": 0,
            "frequency": 15,
            "score": 551,
            "type": "common"
        },
        {
            "include": false,
            "name": "Event_in_Syria",
            "service": "twitter",
            "age": -33,
            "engagement": 0,
            "volume": -1,
            "frequency": -19,
            "score": 1957,
            "type": "common"
        },
        {
            "include": false,
            "name": "mes3freta",
            "service": "twitter",
            "age": -46,
            "engagement": 1,
            "volume": 1,
            "frequency": -44,
            "score": 71,
            "type": "common"
        },
        {
            "include": false,
            "name": "alhayat_syria",
            "service": "twitter",
            "age": -30,
            "engagement": 0,
            "volume": 0,
            "frequency": -7,
            "score": 9192,
            "type": "common"
        },
        {
            "include": false,
            "name": "SyriaAdvisory",
            "service": "twitter",
            "age": 22,
            "engagement": -1,
            "volume": 1,
            "frequency": 30,
            "score": 1753,
            "type": "common"
        },
        {
            "include": true,
            "name": "syrianor",
            "service": "twitter",
            "age": 8,
            "engagement": -1,
            "volume": 0,
            "frequency": 16,
            "score": 9411,
            "type": "common"
        },
        {
            "include": false,
            "name": "SyriaCampaigns",
            "service": "twitter",
            "age": 17,
            "engagement": 0,
            "volume": 0,
            "frequency": 24,
            "score": 2072,
            "type": "common"
        },
        {
            "include": false,
            "name": "syria_children",
            "service": "twitter",
            "age": -17,
            "engagement": -1,
            "volume": -1,
            "frequency": -7,
            "score": 5494,
            "type": "common"
        },
        {
            "include": false,
            "name": "Wafa_Zaidan",
            "service": "twitter",
            "age": 18,
            "engagement": -1,
            "volume": 0,
            "frequency": 26,
            "score": 3739,
            "type": "common"
        },
        {
            "include": false,
            "name": "AliaMalek",
            "service": "twitter",
            "age": -20,
            "engagement": -1,
            "volume": 0,
            "frequency": 1,
            "score": 928,
            "type": "common"
        },
        {
            "include": false,
            "name": "Partisangirl",
            "service": "twitter",
            "age": -19,
            "engagement": 0,
            "volume": 0,
            "frequency": -7,
            "score": 1379,
            "type": "common"
        },
        {
            "include": false,
            "name": "fsa_dam",
            "service": "twitter",
            "age": 29,
            "engagement": 0,
            "volume": 0,
            "frequency": 1,
            "score": 374,
            "type": "common"
        },
        {
            "include": false,
            "name": "SyrianProtests",
            "service": "twitter",
            "age": 49,
            "engagement": 0,
            "volume": 0,
            "frequency": 37,
            "score": 5618,
            "type": "common"
        },
        {
            "include": false,
            "name": "Freedome123",
            "service": "twitter",
            "age": 31,
            "engagement": 0,
            "volume": 0,
            "frequency": 27,
            "score": 5981,
            "type": "common"
        },
        {
            "include": false,
            "name": "OT_48",
            "service": "twitter",
            "age": -24,
            "engagement": 1,
            "volume": 0,
            "frequency": -44,
            "score": 196,
            "type": "common"
        },
        {
            "include": false,
            "name": "Ashtar202",
            "service": "twitter",
            "age": -44,
            "engagement": 0,
            "volume": -1,
            "frequency": -19,
            "score": 4,
            "type": "common"
        },
        {
            "include": false,
            "name": "Faisal_alshagha",
            "service": "twitter",
            "age": -40,
            "engagement": -1,
            "volume": 1,
            "frequency": -19,
            "score": 202,
            "type": "common"
        },
        {
            "include": false,
            "name": "__Asd_",
            "service": "twitter",
            "age": -24,
            "engagement": 0,
            "volume": 0,
            "frequency": -44,
            "score": 313,
            "type": "common"
        },
        {
            "include": false,
            "name": "Sara_Alaskar",
            "service": "twitter",
            "age": 10,
            "engagement": -1,
            "volume": 0,
            "frequency": 17,
            "score": 184,
            "type": "common"
        },
        {
            "include": false,
            "name": "almidanco",
            "service": "twitter",
            "age": 30,
            "engagement": -1,
            "volume": 0,
            "frequency": 1,
            "score": 1050,
            "type": "common"
        },
        {
            "include": false,
            "name": "SyrianProtests",
            "service": "twitter",
            "age": 49,
            "engagement": 0,
            "volume": 0,
            "frequency": 37,
            "score": 5618,
            "type": "common"
        },
        {
            "include": true,
            "name": "HalabTodayTV",
            "service": "twitter",
            "age": -39,
            "engagement": 0,
            "volume": 1,
            "frequency": -19,
            "score": 9415,
            "type": "common"
        },
        {
            "include": false,
            "name": "HalabNews",
            "service": "twitter",
            "age": -46,
            "engagement": -1,
            "volume": 0,
            "frequency": -44,
            "score": 2504,
            "type": "common"
        },
        {
            "include": false,
            "name": "DRmuath1",
            "service": "twitter",
            "age": -46,
            "engagement": 0,
            "volume": 0,
            "frequency": -44,
            "score": 44,
            "type": "common"
        },
        {
            "include": false,
            "name": "Abo_mkiilf",
            "service": "twitter",
            "age": 25,
            "engagement": -1,
            "volume": -1,
            "frequency": 1,
            "score": 125,
            "type": "common"
        },
        {
            "include": false,
            "name": "ahmad_alsobah",
            "service": "twitter",
            "age": -7,
            "engagement": 1,
            "volume": -1,
            "frequency": -7,
            "score": 170,
            "type": "common"
        },
        {
            "include": false,
            "name": "mohazalli",
            "service": "twitter",
            "age": -9,
            "engagement": 0,
            "volume": 0,
            "frequency": -7,
            "score": 3,
            "type": "common"
        },
        {
            "include": true,
            "name": "http://runhaliqa.tumblr.com/",
            "service": "tumblr",
            "age": -50,
            "engagement": 1,
            "volume": 1,
            "frequency": 49,
            "score": 58,
            "type": "crisis"
        },
        {
            "include": true,
            "name": "http://speakup4syrianchildren.tumblr.com/",
            "service": "tumblr",
            "age": 49,
            "engagement": -1,
            "volume": -1,
            "frequency": -50,
            "score": 1250,
            "type": "crisis"
        },
        {
            "include": false,
            "name": "mo7ammedmoh",
            "service": "twitter",
            "age": -25,
            "engagement": 0,
            "volume": 1,
            "frequency": 49,
            "score": 811,
            "type": "crisis"
        },
        {
            "include": true,
            "name": "rooom2012",
            "service": "twitter",
            "age": 49,
            "engagement": 0,
            "volume": 0,
            "frequency": -25,
            "score": 3021,
            "type": "crisis"
        },
        {
            "include": false,
            "name": "mo7ammedmoh",
            "service": "twitter",
            "age": -25,
            "engagement": 0,
            "volume": 1,
            "frequency": 49,
            "score": 811,
            "type": "crisis"
        },
        {
            "include": true,
            "name": "rooom2012",
            "service": "twitter",
            "age": 49,
            "engagement": 0,
            "volume": 0,
            "frequency": -25,
            "score": 3021,
            "type": "crisis"
        },
        {
            "include": false,
            "name": "mo7ammedmoh",
            "service": "twitter",
            "age": -25,
            "engagement": 0,
            "volume": 1,
            "frequency": 49,
            "score": 811,
            "type": "crisis"
        },
        {
            "include": true,
            "name": "rooom2012",
            "service": "twitter",
            "age": 49,
            "engagement": 0,
            "volume": 0,
            "frequency": -25,
            "score": 3021,
            "type": "crisis"
        },
        {
            "include": false,
            "name": "mo7ammedmoh",
            "service": "twitter",
            "age": -25,
            "engagement": 0,
            "volume": 1,
            "frequency": 49,
            "score": 811,
            "type": "crisis"
        },
        {
            "include": false,
            "name": "rooom2012",
            "service": "twitter",
            "age": 49,
            "engagement": 0,
            "volume": 0,
            "frequency": -25,
            "score": 3021,
            "type": "crisis"
        },
        {
            "include": false,
            "name": "mo7ammedmoh",
            "service": "twitter",
            "age": -25,
            "engagement": 0,
            "volume": 1,
            "frequency": 49,
            "score": 811,
            "type": "crisis"
        },
        {
            "include": false,
            "name": "rooom2012",
            "service": "twitter",
            "age": 49,
            "engagement": 0,
            "volume": 0,
            "frequency": -25,
            "score": 3021,
            "type": "crisis"
        },
        {
            "include": false,
            "name": "mo7ammedmoh",
            "service": "twitter",
            "age": -25,
            "engagement": 0,
            "volume": 1,
            "frequency": 49,
            "score": 811,
            "type": "crisis"
        },
        {
            "include": false,
            "name": "rooom2012",
            "service": "twitter",
            "age": 49,
            "engagement": 0,
            "volume": 0,
            "frequency": -25,
            "score": 3021,
            "type": "crisis"
        },
        {
            "include": false,
            "name": "mo7ammedmoh",
            "service": "twitter",
            "age": -25,
            "engagement": 0,
            "volume": 1,
            "frequency": 49,
            "score": 811,
            "type": "crisis"
        },
        {
            "include": false,
            "name": "rooom2012",
            "service": "twitter",
            "age": 49,
            "engagement": 0,
            "volume": 0,
            "frequency": -25,
            "score": 3021,
            "type": "crisis"
        },
        {
            "include": false,
            "name": "mo7ammedmoh",
            "service": "twitter",
            "age": -25,
            "engagement": 0,
            "volume": 1,
            "frequency": 49,
            "score": 811,
            "type": "crisis"
        },
        {
            "include": false,
            "name": "rooom2012",
            "service": "twitter",
            "age": 49,
            "engagement": 0,
            "volume": 0,
            "frequency": -25,
            "score": 3021,
            "type": "crisis"
        },
        {
            "include": false,
            "name": "sa_council",
            "service": "twitter",
            "age": -10,
            "engagement": 0,
            "volume": 1,
            "frequency": -10,
            "score": 241,
            "type": "crisis"
        },
        {
            "include": false,
            "name": "sa_council",
            "service": "twitter",
            "age": -10,
            "engagement": 0,
            "volume": 1,
            "frequency": -10,
            "score": 241,
            "type": "crisis"
        },
        {
            "include": false,
            "name": "sa_council",
            "service": "twitter",
            "age": -10,
            "engagement": 0,
            "volume": 1,
            "frequency": -10,
            "score": 241,
            "type": "crisis"
        },
        {
            "include": false,
            "name": "sa_council",
            "service": "twitter",
            "age": -10,
            "engagement": 0,
            "volume": 1,
            "frequency": -10,
            "score": 241,
            "type": "crisis"
        }
    ],
    "tags": [
        {
            "count": 5,
            "tag": "",
            "type": "common"
        },
        {
            "count": 1,
            "tag": "raining",
            "type": "common"
        },
        {
            "count": 1,
            "tag": "__",
            "type": "common"
        },
        {
            "count": 1,
            "tag": "__",
            "type": "common"
        },
        {
            "count": 21,
            "tag": "yellow",
            "type": "common"
        },
        {
            "count": 1,
            "tag": "Abbas",
            "type": "common"
        },
        {
            "count": 5,
            "tag": "vision:outdoor=0963",
            "type": "common"
        },
        {
            "count": 1,
            "tag": "woods",
            "type": "common"
        },
        {
            "count": 2,
            "tag": "spiders",
            "type": "common"
        },
        {
            "count": 1,
            "tag": "luxuryegypteaccomodations",
            "type": "common"
        },
        {
            "count": 1,
            "tag": "How cool is that?",
            "type": "crisis"
        },
        {
            "count": 1,
            "tag": "cute",
            "type": "crisis"
        },
        {
            "count": 1,
            "tag": "good advice",
            "type": "crisis"
        },
        {
            "count": 8,
            "tag": "",
            "type": "crisis"
        },
        {
            "count": 1,
            "tag": "help",
            "type": "crisis"
        },
        {
            "count": 8,
            "tag": "",
            "type": "crisis"
        },
        {
            "count": 1,
            "tag": "Jisreen",
            "type": "crisis"
        },
        {
            "count": 1,
            "tag": "nabek",
            "type": "crisis"
        },
        {
            "count": 8,
            "tag": "_",
            "type": "crisis"
        },
        {
            "count": 8,
            "tag": "",
            "type": "crisis"
        }
    ]
}